qsiml.py
qsiml-0.0.5.dist-info/METADATA
qsiml-0.0.5.dist-info/WHEEL
qsiml-0.0.5.dist-info/licenses/LICENSE
qsiml-0.0.5.dist-info/RECORD
