Metadata-Version: 2.3
Name: qsiml
Version: 0.0.5
Summary: A simulation of quantum circuits in python
Project-URL: Homepage, https://github.com/MustafaAamir/qsiml
Author-email: Mustafa Aamir <mustafa.290101@gmail.com>, Yusuf Sabuwala <yusuff.0279@gmail.com>
License:                     GNU GENERAL PUBLIC LICENSE
License-File: LICENSE
Keywords: quantum,quantum computing,simulator
Classifier: License :: OSI Approved :: MIT License
Classifier: Operating System :: OS Independent
Classifier: Programming Language :: Python :: 3
Requires-Python: >=3.12
Requires-Dist: numpy
Requires-Dist: tabulate
